README
setup.py
mixpanel/__init__.py
mixpanel_python.egg-info/PKG-INFO
mixpanel_python.egg-info/SOURCES.txt
mixpanel_python.egg-info/dependency_links.txt
mixpanel_python.egg-info/top_level.txt