Metadata-Version: 1.0
Name: mixpanel-python
Version: 0.0.2
Summary: Minimal Mixpanel API Client
Home-page: https://github.com/kortina/mixpanel-python
Author: Andrew Kortina
Author-email: kortina@gmail.com
License: MIT
Keywords: mixpanel
Platform: UNKNOWN
